cleverdiff/__init__.py
cleverdiff/__main__.py
cleverdiff/cleverdiff.py
cleverdiff/contexts.py
cleverdiff/diffhunk.py
cleverdiff/difflist.py
cleverdiff/test_cleverdiff.py
cleverdiff/test_contexts.py
cleverdiff/test_diffhunk.py
cleverdiff/test_difflist.py
cleverdiff/test_data/new.def
cleverdiff/test_data/new2.def
cleverdiff/test_data/ref.def
cleverdiff/test_data/ref2.def
cleverdiff-0.3.dist-info/entry_points.txt
cleverdiff-0.3.dist-info/LICENSE
cleverdiff-0.3.dist-info/WHEEL
cleverdiff-0.3.dist-info/METADATA
cleverdiff-0.3.dist-info/RECORD
