Metadata-Version: 2.1
Name: cleverdiff
Version: 0.3
Summary: A tool for describing multiple differences in files.
Home-page: https://github.com/andrewcbennett/cleverdiff
License: UNKNOWN
Author: Andrew Bennett
Author-email: chudleigh.rivet@gmail.com
Requires-Python: >=3.6
Classifier: License :: OSI Approved :: GNU General Public License v3 or later (GPLv3+)
